science2/__init__.py
science2/__main__.py
science2/lib.py
science2/creating variables/desktop.ini
science2/creating variables/web of science cooccurrences.ipynb
science2/figures/SB-best years.png
science2/figures/SB-time lag.png
science2/figures/auth.agedist.png
science2/figures/auth.prop dead by cohort.png
science2/figures/aysum_example_authordeath.png
science2/figures/cdeath_logreg_Age.png
science2/figures/cdeath_logreg_Cohort.png
science2/figures/cdeath_logreg_Year.png
science2/figures/cit.agedist.png
science2/figures/cit.prop dead by cohort.png
science2/figures/compauth.age.year.png
science2/figures/compcit.age.year.png
science2/figures/cysum_example_authordeath.png
science2/figures/cysum_example_citationdeath.png
science2/figures/desktop.ini
science2/figures/log-log citation degree distribution.png
science2/figures/prop dead by cohort.png
science2/figures/summary_docs_founding.png
science2/figures/totalauth.age.year.png
science2/figures/totalcit.age.year.png
science2/variables/authors.death1.apc-effects
science2/variables/aysum
science2/variables/comebacks
science2/variables/desktop.ini
science2/variables/journals_jw
science2/variables/pubyears.wos.all.uid
science2/variables/wos.all.cysum
science2/variables/wos.all.death3.apc-effects
science2/variables/wos.all.last.apc-effects
science2/variables/wos.all.max.apc-effects
science2/variables/wos.all.propdeath.apc-effects
science2/variables/wos.all.uid.cysum
science2/variables/wos.jstor.cysum
science2/variables/wos.jstor.death3.apc-effects
science2/variables/wos.jstor.last.apc-effects
science2/variables/wos.jstor.max.apc-effects
science2/variables/wos.jstor.propdeath.apc-effects
science2_amcgail-0.0.7.dist-info/LICENSE
science2_amcgail-0.0.7.dist-info/METADATA
science2_amcgail-0.0.7.dist-info/WHEEL
science2_amcgail-0.0.7.dist-info/top_level.txt
science2_amcgail-0.0.7.dist-info/RECORD
