Metadata-Version: 2.1
Name: science2-amcgail
Version: 0.0.7
Summary: Analyzing the evolution of ideas using citation analysis
Home-page: https://github.com/amcgail/science2
Author: Alec McGail
Author-email: amcgail2@gmail.com
License: UNKNOWN
Platform: UNKNOWN
Classifier: Programming Language :: Python :: 3
Classifier: License :: OSI Approved :: MIT License
Classifier: Operating System :: OS Independent
Requires-Python: >=3.6
